ch_api-1.0.2.dist-info/METADATA
ch_api-1.0.2.dist-info/WHEEL
ch_api-1.0.2.dist-info/entry_points.txt
ch_api/__init__.py
ch_api/__version__.py
ch_api/api.py
ch_api/api_settings.py
ch_api/exc.py
ch_api/types/__init__.py
ch_api/types/base.py
ch_api/types/compound_api_types/__init__.py
ch_api/types/compound_api_types/public_data/__init__.py
ch_api/types/compound_api_types/public_data/officer_appointments.py
ch_api/types/compound_api_types/public_data/pagination.py
ch_api/types/compound_api_types/public_data/psc.py
ch_api/types/compound_api_types/public_data/search_companies.py
ch_api/types/compound_api_types/public_data/top_hit.py
ch_api/types/field_types.py
ch_api/types/pagination/__init__.py
ch_api/types/pagination/paginated_list.py
ch_api/types/pagination/types.py
ch_api/types/public_data/__init__.py
ch_api/types/public_data/charges.py
ch_api/types/public_data/company_officers.py
ch_api/types/public_data/company_profile.py
ch_api/types/public_data/company_registers.py
ch_api/types/public_data/disqualifications.py
ch_api/types/public_data/exemptions.py
ch_api/types/public_data/filing_history.py
ch_api/types/public_data/insolvency.py
ch_api/types/public_data/officer_appointments.py
ch_api/types/public_data/officer_changes.py
ch_api/types/public_data/psc.py
ch_api/types/public_data/registered_office.py
ch_api/types/public_data/search.py
ch_api/types/public_data/search_companies.py
ch_api/types/public_data/uk_establishments.py
ch_api/types/settings.py
ch_api/types/shared.py
ch_api/types/test_data_generator.py
ch_api-1.0.2.dist-info/RECORD
