Metadata-Version: 2.1
Name: ch-api
Version: 1.0.2
Summary: UK Companies House API
Keywords: Companies House,CH,restful api,uk,united kingdom
Author-Email: Ilja Orlovs <VRGhost@users.noreply.github.com>
License: MIT
Classifier: Environment :: Console
Classifier: Programming Language :: Python :: 3
Classifier: Programming Language :: Python :: 3.11
Classifier: Programming Language :: Python :: 3.12
Classifier: Programming Language :: Python :: 3.13
Classifier: Development Status :: 4 - Beta
Classifier: Operating System :: POSIX :: Linux
Classifier: Operating System :: MacOS
Classifier: Operating System :: Microsoft :: Windows
Project-URL: Homepage, https://docs.release.art/ch-api/
Project-URL: Documentation, https://docs.release.art/ch-api/
Project-URL: Repository, https://github.com/release-art/ch-api/
Requires-Python: >=3.11
Requires-Dist: httpx>=0.28.1
Requires-Dist: pydantic>=2.12.5
Provides-Extra: dev
Requires-Dist: pytest>=9.0.2; extra == "dev"
Requires-Dist: pytest-mock>=3.15.1; extra == "dev"
Requires-Dist: pytest-cov>=7.0.0; extra == "dev"
Requires-Dist: pytest-asyncio>=1.3.0; extra == "dev"
Requires-Dist: ruff>=0.14.13; extra == "dev"
Requires-Dist: myst-parser>=5.0.0; extra == "dev"
Requires-Dist: sphinx>=9.0.4; extra == "dev"
Requires-Dist: sphinx-autobuild>=2025.8.25; extra == "dev"
Requires-Dist: sphinx-copybutton>=0.5.2; extra == "dev"
Requires-Dist: sphinx-design>=0.7.0; extra == "dev"
Requires-Dist: pydata-sphinx-theme>=0.16.1; extra == "dev"
Requires-Dist: autodoc-pydantic>=2.2.0; extra == "dev"
Requires-Dist: ty>=0.0.14; extra == "dev"
Requires-Dist: pytest-doctestplus>=1.7.1; extra == "dev"
